_primitives/__init__.py
_primitives/argument.py
_primitives/async_context.py
_primitives/awaitable.py
_primitives/callable.py
_primitives/cls.py
_primitives/exceptions.py
_primitives/ignore.py
_primitives/instance.py
primitives/__init__.py
primitives/exceptions.py
primitives-1.8.0.dist-info/LICENSE
primitives-1.8.0.dist-info/WHEEL
primitives-1.8.0.dist-info/METADATA
primitives-1.8.0.dist-info/RECORD
