Metadata-Version: 2.1
Name: primitives
Version: 1.8.0
Summary: Fake objects designed with OOP in mind.
Home-page: https://pypi.org/project/primitives
License: BSD-2-Clause
Author: Artem Malyshev
Author-email: proofit404@gmail.com
Classifier: License :: OSI Approved :: BSD License
Classifier: Programming Language :: Python :: 2
Classifier: Programming Language :: Python :: 2.7
Classifier: Programming Language :: Python :: 3
Classifier: Programming Language :: Python :: 3.10
Classifier: Programming Language :: Python :: 3.4
Classifier: Programming Language :: Python :: 3.5
Classifier: Programming Language :: Python :: 3.6
Classifier: Programming Language :: Python :: 3.7
Classifier: Programming Language :: Python :: 3.8
Classifier: Programming Language :: Python :: 3.9
Classifier: Programming Language :: Python :: Implementation :: CPython
Classifier: Programming Language :: Python :: Implementation :: PyPy
Project-URL: Changelog, https://proofit404.github.io/primitives/changelog
Project-URL: Documentation, https://proofit404.github.io/primitives
Project-URL: Issues, https://github.com/proofit404/primitives/issues
Project-URL: Repository, https://github.com/proofit404/primitives
Project-URL: Twitter, https://twitter.com/proofit404
